{
  "skills": [
    {
      "id": "P",
      "name": "狂戦士の怒り",
      "tags": [
        "自動効果",
        "バフ"
      ],
      "cooldown_text": null,
      "description": "減少体力1%ごとに攻撃速度が1%(↑)、物理ヴァンプが0.2%(↑)増加する。上限は減少体力70%時の攻撃速度70%(↑)、物理ヴァンプ15%(↑)。",
      "table": null
    },
    {
      "id": "Q",
      "name": "斧投げ",
      "tags": [
        "物理",
        "スロウ"
      ],
      "cooldown_text": "7秒",
      "description": "斧を投げて50の物理ダメージ(50 + 120%増加🗡️)を与え、2秒間20%のスロウ効果を付与する。命中した敵チャンピオンは4秒間、物理防御が20%低下する。\n\n斧を拾うと「斧投げ」のクールダウンが4.5秒短縮される。\nモンスターには110%のダメージを与える。",
      "table": {
        "headers": [
          "LV 1",
          "LV 2",
          "LV 3",
          "LV 4"
        ],
        "rows": [
          {
            "label": "コスト",
            "values": [
              "45",
              "50",
              "55",
              "60"
            ]
          },
          {
            "label": "基本ダメージ",
            "values": [
              "50",
              "115",
              "180",
              "245"
            ]
          },
          {
            "label": "スロウ",
            "values": [
              "20%",
              "27.5%",
              "35%",
              "42.5%"
            ]
          }
        ]
      }
    },
    {
      "id": "W",
      "name": "残忍な斧",
      "tags": [
        "バフ"
      ],
      "cooldown_text": "15秒",
      "description": "4秒間、攻撃速度が35%増加する。2.5秒間、108のダメージ(35 + 減少体力の15%)を防ぎ、減少体力の70%を上限とする耐久値のシールドを獲得する。",
      "table": {
        "headers": [
          "LV 1",
          "LV 2",
          "LV 3",
          "LV 4"
        ],
        "rows": [
          {
            "label": "クールダウン",
            "values": [
              "15",
              "14",
              "13",
              "12"
            ]
          },
          {
            "label": "攻撃速度",
            "values": [
              "35%",
              "50%",
              "65%",
              "80%"
            ]
          },
          {
            "label": "シールド",
            "values": [
              "35",
              "70",
              "105",
              "140"
            ]
          }
        ]
      }
    },
    {
      "id": "E",
      "name": "捨て身切り",
      "tags": [
        "確定",
        "機動性"
      ],
      "cooldown_text": "10秒",
      "description": "敵にダッシュして81の確定ダメージ(45 + 55%🗡️)を与える。敵を倒せなかった場合は自分が28の確定ダメージ(18 + 15%🗡️)を受ける。\n\n通常攻撃を行うと「捨て身切り」のクールダウンが1秒短縮される。\n\nモンスターには95%のダメージを与える。",
      "table": {
        "headers": [
          "LV 1",
          "LV 2",
          "LV 3",
          "LV 4"
        ],
        "rows": [
          {
            "label": "クールダウン",
            "values": [
              "10",
              "9",
              "8",
              "7"
            ]
          },
          {
            "label": "基本ダメージ",
            "values": [
              "45",
              "95",
              "145",
              "195"
            ]
          }
        ]
      }
    },
    {
      "id": "R",
      "name": "ラグナロク",
      "tags": [
        "バフ"
      ],
      "cooldown_text": "60秒",
      "description": "自動効果: 物理防御と魔法防御が25増加する。\n\n発動効果: 4秒間行動妨害を受けなくなり、攻撃力が5(5 + 20%🗡️)増加する。さらに発動から1秒間、敵チャンピオンに向かって移動する際に移動速度が20%増加する。敵チャンピオンに対して通常攻撃を行うか「捨て身切り」を発動するたびに、このスキルの効果時間は2.5秒延長される。\n\n「ラグナロク」は行動妨害効果を受けているときにも発動できる。",
      "table": {
        "headers": [
          "LV 1",
          "LV 2",
          "LV 3"
        ],
        "rows": [
          {
            "label": "クールダウン",
            "values": [
              "60",
              "55",
              "50"
            ]
          },
          {
            "label": "防御力",
            "values": [
              "25",
              "35",
              "45"
            ]
          },
          {
            "label": "増加攻撃力",
            "values": [
              "5",
              "15",
              "25"
            ]
          },
          {
            "label": "移動速度",
            "values": [
              "20%",
              "45%",
              "70%"
            ]
          }
        ]
      }
    }
  ]
}