{
  "skills": [
    {
      "id": "P",
      "name": "繊月の刃",
      "tags": [
        "自動効果",
        "魔法"
      ],
      "cooldown_text": null,
      "description": "スキル使用後、4秒間、攻撃速度が30% ( ⬆ )増加する。\n通常攻撃が3回ごとに、周囲の敵に35の魔法ダメージを追加で与える。\nモンスターには75%のダメージを与える。",
      "table": null
    },
    {
      "id": "Q",
      "name": "月影",
      "tags": [
        "魔法"
      ],
      "cooldown_text": "8秒",
      "description": "弧を描くエネルギーを放って60の魔法ダメージ(60 +70% 🔮)を与え、3秒間月光を付与する。",
      "table": {
        "headers": [
          "LV 1",
          "LV 2",
          "LV 3",
          "LV 4"
        ],
        "rows": [
          {
            "label": "クールダウン",
            "values": [
              "8",
              "7",
              "6",
              "5"
            ]
          },
          {
            "label": "コスト",
            "values": [
              "50",
              "55",
              "60",
              "65"
            ]
          },
          {
            "label": "基本ダメージ",
            "values": [
              "60",
              "105",
              "150",
              "195"
            ]
          }
        ]
      }
    },
    {
      "id": "W",
      "name": "朧月の羽衣",
      "tags": [
        "魔法",
        "バフ"
      ],
      "cooldown_text": "13秒",
      "description": "5秒間、3つの月光の玉が自身の周囲を旋回する。玉は敵と接触すると爆発して20の魔法ダメージ(20 +20% 🔮)を与える。\n\nまた、耐久値50(50 +40% 🔮)のシールドを獲得する。3つ目の玉が爆発すると、このシールドの耐久値が50(50 +40% 🔮)増加する。",
      "table": {
        "headers": [
          "LV 1",
          "LV 2",
          "LV 3",
          "LV 4"
        ],
        "rows": [
          {
            "label": "クールダウン",
            "values": [
              "13",
              "11.5",
              "10",
              "8.5"
            ]
          },
          {
            "label": "基本ダメージ",
            "values": [
              "20",
              "35",
              "50",
              "65"
            ]
          },
          {
            "label": "シールド",
            "values": [
              "50",
              "70",
              "90",
              "110"
            ]
          }
        ]
      }
    },
    {
      "id": "E",
      "name": "月下美刃",
      "tags": [
        "魔法",
        "機動性"
      ],
      "cooldown_text": "18秒",
      "description": "敵の近くまでダッシュして40の魔法ダメージ(40 +30% 🔮)を与え、一定範囲内の月光を解除する。\n\n敵に付与された月光を解除すると、「月下美刃」のクールダウンが0.5秒に短縮される。",
      "table": {
        "headers": [
          "LV 1",
          "LV 2",
          "LV 3",
          "LV 4"
        ],
        "rows": [
          {
            "label": "クールダウン",
            "values": [
              "18",
              "16",
              "14",
              "12"
            ]
          },
          {
            "label": "基本ダメージ",
            "values": [
              "40",
              "80",
              "120",
              "160"
            ]
          }
        ]
      }
    },
    {
      "id": "R",
      "name": "崩月",
      "tags": [
        "魔法",
        "スロウ"
      ],
      "cooldown_text": "70秒",
      "description": "月を召喚して、広がっていく領域を照らす。範囲内の敵に20%のスロウ効果を与える。この間、ダイアナは最大1秒間チャージする。チャージが完了すると、崩月の輝きが発動する。チャージ中は、移動およびスキルとスペルの使用が可能。\n付近に敵チャンピオンがいない場合は、このスキルを発動できない。\n\n崩月の輝き: 月光を打ちつけて、敵を月光でマークし、チャージ時間に応じて100(100 + 40% 🔮)-200の魔法ダメージ(200 + 80% 🔮)を与える。対象に2秒間、20%のスロウ効果を与える。",
      "table": {
        "headers": [
          "LV 1",
          "LV 2",
          "LV 3"
        ],
        "rows": [
          {
            "label": "クールダウン",
            "values": [
              "70",
              "65",
              "60"
            ]
          },
          {
            "label": "基本ダメージ",
            "values": [
              "100",
              "160",
              "220"
            ]
          },
          {
            "label": "基本ダメージ",
            "values": [
              "200",
              "320",
              "440"
            ]
          }
        ]
      }
    }
  ]
}