{
  "skills": [
    {
      "id": "P",
      "name": "永遠の渇き",
      "tags": [
        "自動効果",
        "回復"
      ],
      "cooldown_text": null,
      "description": "通常攻撃時効果で12の魔法ダメージ(12 + 20%増加AD + 10%AP)を追加で与える。<br><br>体力が50%未満だった場合は、与ダメージの100%にあたる体力を回復する。",
      "table": null
    },
    {
      "id": "Q",
      "name": "野獣の牙",
      "tags": [
        "魔法",
        "回復"
      ],
      "cooldown_text": "6秒",
      "description": "タップ: 前方にダッシュして対象の敵に噛みつき、70(120%AD + 90%AP)+ 対象の最大体力の6%の魔法ダメージを与え、与ダメージの42.5%の体力を回復する。<br><br>ドラッグ: 対象の背後に回り、相手の移動に追従する。<br><br>通常攻撃時効果を付与する。対象がモンスターの場合、この追加ダメージは100が上限となる。<br>ミニオンには50%の追加ダメージを与える。ミニオンをキルすると、クールダウンが50%短縮される。",
      "table": {
        "headers": [
          "LV 1",
          "LV 2",
          "LV 3",
          "LV 4"
        ],
        "rows": [
          {
            "label": "体力割合ダメージ",
            "values": [
              "6%",
              "7%",
              "8%",
              "9%"
            ]
          },
          {
            "label": "回復",
            "values": [
              "42.5%",
              "55%",
              "67.5%",
              "80%"
            ]
          },
          {
            "label": "モンスターに対する最大ダメージ",
            "values": [
              "100",
              "125",
              "150",
              "175"
            ]
          }
        ]
      }
    },
    {
      "id": "W",
      "name": "血の追跡",
      "tags": [
        "バフ"
      ],
      "cooldown_text": "70秒",
      "description": "自動効果:体力が50%未満の敵チャンピオンをマークし、そのチャンピオンに向かって移動する際に移動速度が40%増加し、体力が50%未満の敵に対しては攻撃速度が60%増加する。体力が35%未満の対象には、これらのボーナスが150%に増加する。<br><br>発動効果: 少しの間視界を広げ、すべての地形を無視し、マップ上の範囲内にいるすべての敵を感知し、最も近くにいる敵チャンピオンを8秒間マークする。チャンピオンと戦闘中は使用できない。<br><br>自動効果で感知できるのは、味方によって体力が50%未満になった敵のみ。",
      "table": {
        "headers": [
          "LV 1",
          "LV 2",
          "LV 3",
          "LV 4"
        ],
        "rows": [
          {
            "label": "クールダウン",
            "values": [
              "70",
              "60",
              "50",
              "40"
            ]
          },
          {
            "label": "移動速度",
            "values": [
              "40%",
              "45%",
              "50%",
              "55%"
            ]
          },
          {
            "label": "攻撃速度",
            "values": [
              "60%",
              "70%",
              "80%",
              "90%"
            ]
          }
        ]
      }
    },
    {
      "id": "E",
      "name": "怒りの咆哮",
      "tags": [
        "バフ",
        "妨害"
      ],
      "cooldown_text": "14秒",
      "description": "最初の発動: 2.5秒間、35%のダメージ軽減効果を獲得する。この効果が終了すると咆哮をあげ、周囲の敵に1秒間フィアー効果を与えて逃亡させる。この際、敵は90%のスロウ効果を受ける。<br><br>再発動: スキルが早めに終了する(ダメージ軽減効果の時間は短くならない)。このスキルを1秒以内に再度使用した場合、ダメージ軽減効果は即座に終了し、スキルは敵にフィアー効果を与えない。しかし、クールダウンは45%短縮される。",
      "table": {
        "headers": [
          "LV 1",
          "LV 2",
          "LV 3",
          "LV 4"
        ],
        "rows": [
          {
            "label": "クールダウン",
            "values": [
              "14",
              "13",
              "12",
              "11"
            ]
          },
          {
            "label": "ダメージ軽減",
            "values": [
              "35%",
              "40%",
              "45%",
              "50%"
            ]
          }
        ]
      }
    },
    {
      "id": "R",
      "name": "絶狼牙連撃",
      "tags": [
        "妨害",
        "機動性"
      ],
      "cooldown_text": "80秒",
      "description": "長い距離をリープする。この距離は自分の移動速度に比例する。最初に対象の敵チャンピオンに命中すると、1.5秒間サプレッション効果を付与する。効果時間中に対象に3回攻撃を行い、通常攻撃時効果を3回適用して、125の魔法ダメージ(125 + 167%増加AD)を与える。<br><br>対象にサプレッション効果を与えている間に与えた全ダメージの100%にあたる体力を回復する。",
      "table": {
        "headers": [
          "LV 1",
          "LV 2",
          "LV 3"
        ],
        "rows": [
          {
            "label": "クールダウン",
            "values": [
              "80",
              "70",
              "60"
            ]
          },
          {
            "label": "基本ダメージ",
            "values": [
              "125",
              "300",
              "475"
            ]
          }
        ]
      }
    }
  ]
}